deb_pkg_tools/__init__.py
deb_pkg_tools/cache.py
deb_pkg_tools/checks.py
deb_pkg_tools/cli.py
deb_pkg_tools/compat.py
deb_pkg_tools/config.py
deb_pkg_tools/control.py
deb_pkg_tools/deb822.py
deb_pkg_tools/deps.py
deb_pkg_tools/gpg.py
deb_pkg_tools/package.py
deb_pkg_tools/printer.py
deb_pkg_tools/repo.py
deb_pkg_tools/tests.py
deb_pkg_tools/utils.py
deb_pkg_tools/version/__init__.py
deb_pkg_tools/version/native.py
deb_pkg_tools-8.4.dist-info/LICENSE.txt
deb_pkg_tools-8.4.dist-info/METADATA
deb_pkg_tools-8.4.dist-info/WHEEL
deb_pkg_tools-8.4.dist-info/entry_points.txt
deb_pkg_tools-8.4.dist-info/top_level.txt
deb_pkg_tools-8.4.dist-info/RECORD
